pre_commit_commit_msg_hooks/__init__.py
pre_commit_commit_msg_hooks/check_description_max_length.py
pre_commit_commit_msg_hooks/check_second_line_empty.py
pre_commit_commit_msg_hooks/check_summary_capitalized.py
pre_commit_commit_msg_hooks/check_summary_conjunction.py
pre_commit_commit_msg_hooks/check_summary_imperative.py
pre_commit_commit_msg_hooks/check_summary_max_length.py
pre_commit_commit_msg_hooks/check_summary_min_length.py
pre_commit_commit_msg_hooks/check_summary_punctuation.py
pre_commit_commit_msg_hooks/common.py
pre_commit_commit_msg_hooks/verbs-wordlist.txt
pre_commit_commit_msg_hooks-0.1.0.dist-info/entry_points.txt
pre_commit_commit_msg_hooks-0.1.0.dist-info/LICENSE
pre_commit_commit_msg_hooks-0.1.0.dist-info/WHEEL
pre_commit_commit_msg_hooks-0.1.0.dist-info/METADATA
pre_commit_commit_msg_hooks-0.1.0.dist-info/RECORD
