Metadata-Version: 2.1
Name: pre-commit-commit-msg-hooks
Version: 0.1.0
Summary: A collection of checks for the commit-msg for pre-commit.
Home-page: https://github.com/rlindsgaard/pre-commit-commit-msg-hooks
License: MIT
Author: Ronni Elken Lindsgaard
Author-email: ronni.lindsgaard@gmail.com
Requires-Python: >=3.9,<4.0
Classifier: Intended Audience :: Developers
Classifier: License :: OSI Approved :: MIT License
Classifier: Programming Language :: Python :: 3
Classifier: Programming Language :: Python :: 3.10
Classifier: Programming Language :: Python :: 3.9
Classifier: Topic :: Software Development :: Version Control :: Git
Project-URL: Repository, https://github.com/rlindsgaard/pre-commit-commit-msg-hooks
